tabebm/TabEBM.py
tabebm/__init__.py
tabebm-2024.10.5.dist-info/LICENSE
tabebm-2024.10.5.dist-info/METADATA
tabebm-2024.10.5.dist-info/WHEEL
tabebm-2024.10.5.dist-info/top_level.txt
tabebm-2024.10.5.dist-info/RECORD
