Metadata-Version: 2.1
Name: tabebm
Version: 2024.10.5
Summary: Official implementation of "TabEBM: A Tabular Data Augmentation Method with Class-Specific Energy-Based Models", NeurIPS 2024.
Home-page: https://github.com/andreimargeloiu/TabEBM
Author: Andrei Margeloiu, Xiangjian Jiang, Nikola Simidjievski, Mateja Jamnik
Author-email: silencejiang12138@gmail.com
License: Apache Software License
Classifier: License :: OSI Approved :: Apache Software License
Classifier: Programming Language :: Python :: 3
Classifier: Programming Language :: Python :: 3.10
Requires-Python: >=3.10.0
License-File: LICENSE
Requires-Dist: matplotlib
Requires-Dist: matplotlib-inline
Requires-Dist: numpy
Requires-Dist: scipy
Requires-Dist: tabpfn
